pyadvincekit/__init__.py
pyadvincekit/auth/__init__.py
pyadvincekit/auth/jwt_auth.py
pyadvincekit/auth/middleware.py
pyadvincekit/auth/permissions.py
pyadvincekit/core/__init__.py
pyadvincekit/core/api_generator.py
pyadvincekit/core/app_factory.py
pyadvincekit/core/auto_api.py
pyadvincekit/core/auto_api_config.py
pyadvincekit/core/auto_api_manager.py
pyadvincekit/core/code_generator.py
pyadvincekit/core/config.py
pyadvincekit/core/database.py
pyadvincekit/core/database_extractor.py
pyadvincekit/core/database_generator.py
pyadvincekit/core/excel_generator.py
pyadvincekit/core/excel_parser.py
pyadvincekit/core/exception_handler.py
pyadvincekit/core/exceptions.py
pyadvincekit/core/middleware.py
pyadvincekit/core/migration.py
pyadvincekit/core/response.py
pyadvincekit/core/router_discovery.py
pyadvincekit/core/scheduler.py
pyadvincekit/core/service_client.py
pyadvincekit/core/service_provider.py
pyadvincekit/core/trace.py
pyadvincekit/crud/__init__.py
pyadvincekit/crud/base.py
pyadvincekit/decorators/__init__.py
pyadvincekit/decorators/transaction.py
pyadvincekit/docs/__init__.py
pyadvincekit/docs/decorators.py
pyadvincekit/docs/file_scanner.py
pyadvincekit/docs/registry.py
pyadvincekit/docs/scanner.py
pyadvincekit/logging/__init__.py
pyadvincekit/logging/handlers.py
pyadvincekit/models/__init__.py
pyadvincekit/models/base.py
pyadvincekit/schemas/__init__.py
pyadvincekit/schemas/common.py
pyadvincekit/utils/__init__.py
pyadvincekit/utils/common.py
pyadvincekit/utils/cron_parser.py
pyadvincekit/utils/date_utils.py
pyadvincekit/utils/datetime_utils.py
pyadvincekit/utils/http_utils.py
pyadvincekit/utils/money_utils.py
pyadvincekit/utils/security.py
pyadvincekit/utils/serializers.py
pyadvincekit/utils/validators.py
pyadvincekit-0.2.1.dist-info/METADATA
pyadvincekit-0.2.1.dist-info/WHEEL
pyadvincekit-0.2.1.dist-info/entry_points.txt
pyadvincekit-0.2.1.dist-info/licenses/LICENSE
pyadvincekit-0.2.1.dist-info/RECORD
