Metadata-Version: 2.4
Name: pyadvincekit
Version: 0.2.1
Summary: 高内聚、易扩展、符合团队规范的Python Web开发基础框架
Project-URL: Homepage, https://github.com/pyadvincekit/pyadvincekit
Project-URL: Documentation, https://pyadvincekit.readthedocs.io
Project-URL: Repository, https://github.com/pyadvincekit/pyadvincekit
Project-URL: Issues, https://github.com/pyadvincekit/pyadvincekit/issues
Project-URL: Changelog, https://github.com/pyadvincekit/pyadvincekit/blob/main/CHANGELOG.md
Author-email: PyAdvanceKit Team <team@pyadvincekit.com>
Maintainer-email: PyAdvanceKit Team <team@pyadvincekit.com>
License: MIT License
License-File: LICENSE
Keywords: async,auth,crud,excel,fastapi,middleware,orm,sqlalchemy,web-framework
Classifier: Development Status :: 3 - Alpha
Classifier: Framework :: FastAPI
Classifier: Intended Audience :: Developers
Classifier: License :: OSI Approved :: MIT License
Classifier: Programming Language :: Python :: 3
Classifier: Programming Language :: Python :: 3.8
Classifier: Programming Language :: Python :: 3.9
Classifier: Programming Language :: Python :: 3.10
Classifier: Programming Language :: Python :: 3.11
Classifier: Programming Language :: Python :: 3.12
Classifier: Topic :: Database
Classifier: Topic :: Internet :: WWW/HTTP :: HTTP Servers
Classifier: Topic :: Software Development :: Libraries :: Python Modules
Requires-Python: >=3.8
Requires-Dist: aiohttp>=3.8.0
Requires-Dist: aiosqlite>=0.19.0
Requires-Dist: alembic>=1.12.0
Requires-Dist: bcrypt>=4.0.0
Requires-Dist: cryptography>=41.0.0
Requires-Dist: email-validator>=2.0.0
Requires-Dist: fastapi>=0.104.0
Requires-Dist: openpyxl>=3.0.0
Requires-Dist: pandas>=1.5.0
Requires-Dist: passlib[bcrypt]>=1.7.4
Requires-Dist: pydantic-settings>=2.0.0
Requires-Dist: pydantic>=2.0.0
Requires-Dist: python-dateutil>=2.8.0
Requires-Dist: python-jose[cryptography]>=3.3.0
Requires-Dist: pytz>=2023.3
Requires-Dist: requests>=2.31.0
Requires-Dist: sqlalchemy>=2.0.0
Requires-Dist: structlog>=23.0.0
Requires-Dist: uvicorn[standard]>=0.24.0
Requires-Dist: xlrd>=2.0.0
Provides-Extra: all
Requires-Dist: aiomysql>=0.2.0; extra == 'all'
Requires-Dist: asyncpg>=0.29.0; extra == 'all'
Requires-Dist: black>=23.0.0; extra == 'all'
Requires-Dist: flake8>=6.0.0; extra == 'all'
Requires-Dist: httpx>=0.25.0; extra == 'all'
Requires-Dist: isort>=5.12.0; extra == 'all'
Requires-Dist: mkdocs-material>=9.0.0; extra == 'all'
Requires-Dist: mkdocs>=1.5.0; extra == 'all'
Requires-Dist: mkdocstrings[python]>=0.23.0; extra == 'all'
Requires-Dist: mypy>=1.5.0; extra == 'all'
Requires-Dist: pre-commit>=3.0.0; extra == 'all'
Requires-Dist: psycopg2-binary>=2.9.0; extra == 'all'
Requires-Dist: pymysql>=1.1.0; extra == 'all'
Requires-Dist: pytest-asyncio>=0.21.0; extra == 'all'
Requires-Dist: pytest-cov>=4.0.0; extra == 'all'
Requires-Dist: pytest>=7.0.0; extra == 'all'
Provides-Extra: dev
Requires-Dist: black>=23.0.0; extra == 'dev'
Requires-Dist: flake8>=6.0.0; extra == 'dev'
Requires-Dist: httpx>=0.25.0; extra == 'dev'
Requires-Dist: isort>=5.12.0; extra == 'dev'
Requires-Dist: mypy>=1.5.0; extra == 'dev'
Requires-Dist: pre-commit>=3.0.0; extra == 'dev'
Requires-Dist: pytest-asyncio>=0.21.0; extra == 'dev'
Requires-Dist: pytest-cov>=4.0.0; extra == 'dev'
Requires-Dist: pytest>=7.0.0; extra == 'dev'
Provides-Extra: docs
Requires-Dist: mkdocs-material>=9.0.0; extra == 'docs'
Requires-Dist: mkdocs>=1.5.0; extra == 'docs'
Requires-Dist: mkdocstrings[python]>=0.23.0; extra == 'docs'
Provides-Extra: mysql
Requires-Dist: aiomysql>=0.2.0; extra == 'mysql'
Requires-Dist: pymysql>=1.1.0; extra == 'mysql'
Provides-Extra: postgresql
Requires-Dist: asyncpg>=0.29.0; extra == 'postgresql'
Requires-Dist: psycopg2-binary>=2.9.0; extra == 'postgresql'
